[{"name":"ELK","path":"api/tags/ELK.json","count":9},{"name":"Beats","path":"api/tags/Beats.json","count":3},{"name":"hide","path":"api/tags/hide.json","count":25},{"name":"Elasticsearch","path":"api/tags/Elasticsearch.json","count":2},{"name":"Logstash","path":"api/tags/Logstash.json","count":1},{"name":"MetricBeat","path":"api/tags/MetricBeat.json","count":1},{"name":"Linux","path":"api/tags/Linux.json","count":1},{"name":"VM","path":"api/tags/VM.json","count":1},{"name":"lifeme","path":"api/tags/lifeme.json","count":3},{"name":"yper-V","path":"api/tags/yper-V.json","count":1},{"name":"IDEA","path":"api/tags/IDEA.json","count":1},{"name":"node","path":"api/tags/node.json","count":1},{"name":"github","path":"api/tags/github.json","count":2},{"name":"sentinel","path":"api/tags/sentinel.json","count":9},{"name":"java","path":"api/tags/java.json","count":12},{"name":"springboot","path":"api/tags/springboot.json","count":11},{"name":"springboot-admin","path":"api/tags/springboot-admin.json","count":1},{"name":"Eureka","path":"api/tags/Eureka.json","count":1},{"name":"Feign","path":"api/tags/Feign.json","count":1},{"name":"Ribbon","path":"api/tags/Ribbon.json","count":1},{"name":"Turbine","path":"api/tags/Turbine.json","count":1},{"name":"Zuul","path":"api/tags/Zuul.json","count":1},{"name":"Bus","path":"api/tags/Bus.json","count":1},{"name":"tomcat","path":"api/tags/tomcat.json","count":1},{"name":"WSL，Redis","path":"api/tags/WSL，Redis.json","count":1},{"name":"WSL，Windows","path":"api/tags/WSL，Windows.json","count":2},{"name":"hadoop","path":"api/tags/hadoop.json","count":1},{"name":"quartz","path":"api/tags/quartz.json","count":1},{"name":"jsp","path":"api/tags/jsp.json","count":1},{"name":"jar","path":"api/tags/jar.json","count":2},{"name":"interview","path":"api/tags/interview.json","count":1},{"name":"jasypt","path":"api/tags/jasypt.json","count":1},{"name":"limiting","path":"api/tags/limiting.json","count":2},{"name":"git","path":"api/tags/git.json","count":1},{"name":"yarn","path":"api/tags/yarn.json","count":1},{"name":"hexo","path":"api/tags/hexo.json","count":1},{"name":"maven","path":"api/tags/maven.json","count":1},{"name":"FileBeat","path":"api/tags/FileBeat.json","count":1},{"name":"Kibana","path":"api/tags/Kibana.json","count":1},{"name":"stream","path":"api/tags/stream.json","count":1},{"name":"h2","path":"api/tags/h2.json","count":1},{"name":"Config","path":"api/tags/Config.json","count":1}]